<?xml version="1.0" standalone="yes"?>
<!--VDS: Configuration version specific for Test Data Set Generator 	-->
<!--VDS: to be used for DFEP and S3-PDGS Test Data Set building		-->
<Sentinel3L0ProductDescription>
	<L0ProductDescriptor>
    		<SatelliteName>SENTINEL3</SatelliteName>
    		<SourcePacketHeaderSize>6</SourcePacketHeaderSize>
    		<AnnotationSize>0</AnnotationSize>
		<RefDocName>S1-IF-ASD-PL-0007</RefDocName>
		<AcquisitionReportFileType>ACQREPORT_</AcquisitionReportFileType>
		<AnnotationIsInUTC>true</AnnotationIsInUTC>
    		<NumberOfProducts>13</NumberOfProducts>
		<Product1>
			<Id>OL_0_EFR</Id>
			<CCSDSVersion>0</CCSDSVersion>
			<DataFieldHeaderLength>12</DataFieldHeaderLength>
			<ApplicationDataLength>33562</ApplicationDataLength>
			<PacketErrorControlLength>2</PacketErrorControlLength>
			<List_of_APID count="5">
    				<APID>1056</APID>
    				<APID>1072</APID>
    				<APID>1088</APID>
    				<APID>1104</APID>
    				<APID>1120</APID>
			</List_of_APID>
			<Channel>0</Channel>
			<VCID>1</VCID>
			<SensorName>OLCI</SensorName>
			<SensorMode></SensorMode>
			<SegmentedPacketsFlag>false</SegmentedPacketsFlag>
			<DeltaNominalTime unit="ms">43.835529</DeltaNominalTime>
			<GapThresold unit="ms">15000</GapThresold>        
			<Description>OLCI Observation Cameras</Description>        
    		</Product1>
		<Product2>
			<Id>OL_0_CR1</Id>
			<CCSDSVersion>0</CCSDSVersion>
			<DataFieldHeaderLength>12</DataFieldHeaderLength>
			<ApplicationDataLength>33562</ApplicationDataLength>
			<PacketErrorControlLength>2</PacketErrorControlLength>
			<List_of_APID count="5">
    				<APID>1057</APID>
    				<APID>1073</APID>
    				<APID>1089</APID>
    				<APID>1105</APID>
    				<APID>1121</APID>
			</List_of_APID>
			<Channel>0</Channel>
			<VCID>2</VCID>
			<SensorName>OLCI</SensorName>
			<SensorMode></SensorMode>
			<SegmentedPacketsFlag>false</SegmentedPacketsFlag>
			<DeltaNominalTime unit="ms">43.835529</DeltaNominalTime>
			<GapThresold unit="ms">15000</GapThresold>        
			<Description>OLCI Observation Calibration Camera</Description>        
    		</Product2>
		<Product3>
			<Id>SL_0_SLT</Id>
			<CCSDSVersion>0</CCSDSVersion>
			<DataFieldHeaderLength>12</DataFieldHeaderLength>
			<ApplicationDataLength>4230</ApplicationDataLength>
			<PacketErrorControlLength>2</PacketErrorControlLength>
			<List_of_APID count="60">
    				<APID>1184</APID>
    				<APID>1184</APID>
    				<APID>1184</APID>
    				<APID>1184</APID>
    				<APID>1184</APID>
    				<APID>1185</APID>
    				<APID>1185</APID>
    				<APID>1185</APID>
    				<APID>1185</APID>
    				<APID>1185</APID>			
    				<APID>1186</APID>
    				<APID>1186</APID>
    				<APID>1186</APID>
    				<APID>1186</APID>
    				<APID>1186</APID>
    				<APID>1187</APID>
    				<APID>1187</APID>
    				<APID>1187</APID>
    				<APID>1187</APID>
    				<APID>1187</APID>
    				<APID>1188</APID>
    				<APID>1188</APID>
    				<APID>1188</APID>
    				<APID>1188</APID>
    				<APID>1188</APID>
    				<APID>1189</APID>
    				<APID>1189</APID>
    				<APID>1189</APID>
    				<APID>1189</APID>
    				<APID>1189</APID>
    				<APID>1190</APID>
    				<APID>1190</APID>
    				<APID>1190</APID>
    				<APID>1190</APID>
    				<APID>1190</APID>
    				<APID>1191</APID>
    				<APID>1191</APID>
    				<APID>1191</APID>
    				<APID>1191</APID>
    				<APID>1191</APID>
    				<APID>1192</APID>
    				<APID>1192</APID>
    				<APID>1192</APID>
    				<APID>1192</APID>
    				<APID>1192</APID>
    				<APID>1193</APID>
    				<APID>1193</APID>
    				<APID>1193</APID>
    				<APID>1193</APID>
    				<APID>1193</APID>
    				<APID>1194</APID>
    				<APID>1194</APID>
    				<APID>1194</APID>
    				<APID>1194</APID>
    				<APID>1194</APID>
    				<APID>1195</APID>
    				<APID>1195</APID>
    				<APID>1195</APID>
    				<APID>1195</APID>
    				<APID>1195</APID>
 			</List_of_APID>
			<Channel>0</Channel>
			<VCID>3</VCID>
			<SensorName>SLSTR</SensorName>
			<SensorMode></SensorMode>
			<SegmentedPacketsFlag>false</SegmentedPacketsFlag>
			<DeltaNominalTime unit="ms">300</DeltaNominalTime>
			<GapThresold unit="ms">15000</GapThresold>        
			<Description>SLSTR</Description>        
    		</Product3>
		<Product4>
			<Id>SR_0_SRA_LOW</Id>
			<CCSDSVersion>0</CCSDSVersion>
			<DataFieldHeaderLength>12</DataFieldHeaderLength>
			<ApplicationDataLength>568</ApplicationDataLength>
			<PacketErrorControlLength>2</PacketErrorControlLength>
			<List_of_APID count="1">
    				<APID>1446</APID>
			</List_of_APID>
			<Channel>0</Channel>
			<VCID>4</VCID>
			<SensorName>SRAL Low Resolution Mode Echo</SensorName>
			<SensorMode></SensorMode>
			<SegmentedPacketsFlag>false</SegmentedPacketsFlag>
			<DeltaNominalTime unit="ms">51.130435</DeltaNominalTime>
			<GapThresold unit="ms">15000</GapThresold>        
			<Description>SRAL Low Resolution Mode Echo</Description>        
    		</Product4>
		<Product5>
			<Id>SR_0_SRA_ECH</Id>
			<CCSDSVersion>0</CCSDSVersion>
			<DataFieldHeaderLength>12</DataFieldHeaderLength>
			<ApplicationDataLength>17464</ApplicationDataLength>
			<PacketErrorControlLength>2</PacketErrorControlLength>
			<List_of_APID count="1">
    				<APID>1447</APID>
			</List_of_APID>
			<Channel>0</Channel>
			<VCID>5</VCID>
			<SensorName>SRAL</SensorName>
			<SensorMode></SensorMode>
			<SegmentedPacketsFlag>false</SegmentedPacketsFlag>
			<DeltaNominalTime unit="ms">12.735318</DeltaNominalTime>
			<GapThresold unit="ms">15000</GapThresold>        
			<Description>SRAL Echo</Description>        
    		</Product5>
		<Product6>
			<Id>SR_0_SRA_CAL</Id>
			<CCSDSVersion>0</CCSDSVersion>
			<DataFieldHeaderLength>12</DataFieldHeaderLength>
			<ApplicationDataLength>12780</ApplicationDataLength>
			<PacketErrorControlLength>2</PacketErrorControlLength>
			<List_of_APID count="6">
    				<APID>1440</APID>
    				<APID>1441</APID>
    				<APID>1442</APID>
    				<APID>1443</APID>
    				<APID>1444</APID>
    				<APID>1445</APID>
			</List_of_APID>
			<Channel>0</Channel>
			<VCID>6</VCID>
			<SensorName>SRAL</SensorName>
			<SensorMode></SensorMode>
			<SegmentedPacketsFlag>false</SegmentedPacketsFlag>
			<DeltaNominalTime unit="ms">24.320151</DeltaNominalTime>
			<GapThresold unit="ms">15000</GapThresold>        
			<Description>SRAL Calibration</Description>        
    		</Product6>
		<Product7>
			<Id>MW_0_MWR</Id>
			<CCSDSVersion>0</CCSDSVersion>
			<DataFieldHeaderLength>12</DataFieldHeaderLength>
			<ApplicationDataLength>38</ApplicationDataLength>
			<PacketErrorControlLength>2</PacketErrorControlLength>
			<List_of_APID count="1">
    				<APID>1323</APID>
			</List_of_APID>
			<Channel>0</Channel>
			<VCID>7</VCID>
			<SensorName>MWR</SensorName>
			<SensorMode></SensorMode>
			<SegmentedPacketsFlag>false</SegmentedPacketsFlag>
			<DeltaNominalTime unit="ms">152.883</DeltaNominalTime>
			<GapThresold unit="ms">15000</GapThresold>        
			<Description>MWR</Description>        
    		</Product7>
		<Product8>
			<Id>GN_0_GNS</Id>
			<CCSDSVersion>0</CCSDSVersion>
			<DataFieldHeaderLength>12</DataFieldHeaderLength>
			<ApplicationDataLength>108</ApplicationDataLength>
			<PacketErrorControlLength>2</PacketErrorControlLength>
			<List_of_APID count="1">
    				<APID>774</APID>
			</List_of_APID>
			<Channel>0</Channel>
			<VCID>8</VCID>
			<SensorName>GNSS</SensorName>
			<SensorMode></SensorMode>
			<SegmentedPacketsFlag>false</SegmentedPacketsFlag>
			<DeltaNominalTime unit="ms">51.2</DeltaNominalTime>
			<GapThresold unit="ms">15000</GapThresold>        
			<Description>GNSS</Description>        
    		</Product8>
		<Product9>
			<Id>DO_0_NAV</Id>
			<CCSDSVersion>0</CCSDSVersion>
			<DataFieldHeaderLength>12</DataFieldHeaderLength>
			<ApplicationDataLength>76</ApplicationDataLength>
			<PacketErrorControlLength>2</PacketErrorControlLength>
			<List_of_APID count="5">
    				<APID>1705</APID>
    				<APID>1709</APID>
    				<APID>1710</APID>
    				<APID>1702</APID>
    				<APID>1707</APID>
			</List_of_APID>
			<Channel>0</Channel>
			<VCID>9</VCID>
			<SensorName>DORIS</SensorName>
			<SensorMode></SensorMode>
			<SegmentedPacketsFlag>false</SegmentedPacketsFlag>
			<DeltaNominalTime unit="ms">192</DeltaNominalTime>
			<GapThresold unit="ms">15000</GapThresold>        
			<Description>DORIS</Description>        
    		</Product9>
		<Product10>
			<Id>PF_HKTM</Id>
			<CCSDSVersion>0</CCSDSVersion>
			<DataFieldHeaderLength>12</DataFieldHeaderLength>
			<ApplicationDataLength>236</ApplicationDataLength>
			<PacketErrorControlLength>2</PacketErrorControlLength>
			<List_of_APID count="1">
    				<APID>4</APID>
			</List_of_APID>
			<Channel>0</Channel>
			<VCID>10</VCID>
			<SensorName>PF_HKTM</SensorName>
			<SensorMode></SensorMode>
			<SegmentedPacketsFlag>false</SegmentedPacketsFlag>
			<DeltaNominalTime unit="ms">102.4</DeltaNominalTime>
			<GapThresold unit="ms">15000</GapThresold>        
			<Description>Platform Housekeeping Telemetry</Description>        
    		</Product10>
		<Product11>
			<Id>PL_HKTM</Id>
			<CCSDSVersion>0</CCSDSVersion>
			<DataFieldHeaderLength>12</DataFieldHeaderLength>
			<ApplicationDataLength>72</ApplicationDataLength>
			<PacketErrorControlLength>2</PacketErrorControlLength>
			<List_of_APID count="5">
    				<APID>1028</APID>
    				<APID>1196</APID>
    				<APID>1412</APID>
    				<APID>1284</APID>
    				<APID>772</APID>
			</List_of_APID>
			<Channel>0</Channel>
			<VCID>11</VCID>
			<SensorName>PL_HKTM</SensorName>
			<SensorMode></SensorMode>
			<SegmentedPacketsFlag>false</SegmentedPacketsFlag>
			<DeltaNominalTime unit="ms">184</DeltaNominalTime>
			<GapThresold unit="ms">15000</GapThresold>        
			<Description>Payload Housekeeping Telemetry</Description>        
    		</Product11>
		<Product12>
			<Id>TM_0_NAT</Id>
			<CCSDSVersion>0</CCSDSVersion>
			<DataFieldHeaderLength>12</DataFieldHeaderLength>
			<ApplicationDataLength>101</ApplicationDataLength>
			<PacketErrorControlLength>2</PacketErrorControlLength>
			<List_of_APID count="1">
    				<APID>361</APID>
			</List_of_APID>
			<Channel>0</Channel>
			<VCID>12</VCID>
			<SensorName>NAVATT</SensorName>
			<SensorMode></SensorMode>
			<SegmentedPacketsFlag>false</SegmentedPacketsFlag>
			<DeltaNominalTime unit="ms">48.4</DeltaNominalTime>
			<GapThresold unit="ms">15000</GapThresold>        
			<Description>Navigation/Attitude Data</Description>        
    		</Product12>
		<Product13>
			<Id>IDLE_PACK_</Id>
			<CCSDSVersion>4</CCSDSVersion>
			<DataFieldHeaderLength>0</DataFieldHeaderLength>
			<ApplicationDataLength>1902</ApplicationDataLength>
			<PacketErrorControlLength>0</PacketErrorControlLength>
        		<List_of_APID count="1">
				<APID>2047</APID>
			</List_of_APID>
			<Channel>0</Channel>
			<VCID>63</VCID>
			<SensorName>IDLE</SensorName>
			<SensorMode>IDLE</SensorMode>
			<SegmentedPacketsFlag>false</SegmentedPacketsFlag>
			<DeltaNominalTime unit="ms">0.06011421701</DeltaNominalTime>
			<GapThresold unit="ms">0</GapThresold>        
			<Description>Idle Frame</Description>        
    		</Product13>
	</L0ProductDescriptor>
</Sentinel3L0ProductDescription>
